napari_xgboost/__init__.py
napari_xgboost/_widget.py
napari_xgboost/napari.yaml
napari_xgboost/_tests/__init__.py
napari_xgboost/_tests/test_widget.py
napari_xgboost-0.1.0.dist-info/LICENSE
napari_xgboost-0.1.0.dist-info/METADATA
napari_xgboost-0.1.0.dist-info/WHEEL
napari_xgboost-0.1.0.dist-info/entry_points.txt
napari_xgboost-0.1.0.dist-info/top_level.txt
napari_xgboost-0.1.0.dist-info/RECORD
