Metadata-Version: 2.1
Name: napari-xgboost
Version: 0.1.0
Summary: A plugin for pixel classification using XGBoost
Author: Robert Haase
Author-email: robert.haase@uni-leipzig.de
License: 
Project-URL: Bug Tracker, https://github.com/haesleinhuepf/napari-xgboost/issues
Project-URL: Documentation, https://github.com/haesleinhuepf/napari-xgboost#README.md
Project-URL: Source Code, https://github.com/haesleinhuepf/napari-xgboost
Project-URL: User Support, https://github.com/haesleinhuepf/napari-xgboost/issues
Classifier: Development Status :: 2 - Pre-Alpha
Classifier: Framework :: napari
Classifier: Intended Audience :: Developers
Classifier: License :: OSI Approved :: BSD License
Classifier: Operating System :: OS Independent
Classifier: Programming Language :: Python
Classifier: Programming Language :: Python :: 3
Classifier: Programming Language :: Python :: 3 :: Only
Classifier: Programming Language :: Python :: 3.9
Classifier: Programming Language :: Python :: 3.10
Classifier: Programming Language :: Python :: 3.11
Classifier: Programming Language :: Python :: 3.12
Classifier: Topic :: Scientific/Engineering :: Image Processing
Requires-Python: >=3.9
License-File: LICENSE
Requires-Dist: numpy
Requires-Dist: magicgui
Requires-Dist: qtpy
Requires-Dist: scikit-image
Requires-Dist: xgboost
Requires-Dist: apoc
Provides-Extra: testing
Requires-Dist: tox ; extra == 'testing'
Requires-Dist: pytest ; extra == 'testing'
Requires-Dist: pytest-cov ; extra == 'testing'
Requires-Dist: pytest-qt ; extra == 'testing'
Requires-Dist: napari ; extra == 'testing'
Requires-Dist: pyqt5 ; extra == 'testing'
